FisherExactTest/FisherExactTest.py
FisherExactTest/__init__.py
FisherExactTest/__version__.py
FisherExactTest-1.0.1.dist-info/LICENSE
FisherExactTest-1.0.1.dist-info/METADATA
FisherExactTest-1.0.1.dist-info/WHEEL
FisherExactTest-1.0.1.dist-info/top_level.txt
FisherExactTest-1.0.1.dist-info/RECORD
